README.rst
setup.py
release/__init__.py
release/main.py
release_py.egg-info/PKG-INFO
release_py.egg-info/SOURCES.txt
release_py.egg-info/dependency_links.txt
release_py.egg-info/entry_points.txt
release_py.egg-info/requires.txt
release_py.egg-info/top_level.txt