Metadata-Version: 1.1
Name: release-py
Version: 1.2.1
Summary: a utility for enforcing release process and automating build versioning with git
Home-page: https://github.com/eddking/release-py
Author: Edmund King
Author-email: edmundking2002@yahoo.co.uk
License: MIT
Download-URL: https://github.com/eddking/release-py/tarball/1.2.1
Keywords: release,git,versioning
Platform: UNKNOWN
Classifier: Development Status :: 3 - Alpha
Classifier: Intended Audience :: Developers
Classifier: Programming Language :: Python :: 2.7
